README.rst
setup.py
FileSearchApp/__init__.py
FileSearchApp/file_search_app.py
FileSearchApp.egg-info/PKG-INFO
FileSearchApp.egg-info/SOURCES.txt
FileSearchApp.egg-info/dependency_links.txt
FileSearchApp.egg-info/entry_points.txt
FileSearchApp.egg-info/top_level.txt