Metadata-Version: 2.1
Name: FileSearchApp
Version: 0.1
Summary: Script for checking folder and all of its sub-folders for occurrence of a given string in all of its files.
Home-page: https://github.com/urosjevremovic/File-Search-App
Author: Uros Jevremovic
Author-email: jevremovic.uros91@gmail.com
License: MIT
Platform: UNKNOWN
